puppy/__init__.py
puppy/puppy.py
puppy/test_puppy.py
puppy_pubsub-0.1.dist-info/DESCRIPTION.rst
puppy_pubsub-0.1.dist-info/METADATA
puppy_pubsub-0.1.dist-info/RECORD
puppy_pubsub-0.1.dist-info/WHEEL
puppy_pubsub-0.1.dist-info/metadata.json
puppy_pubsub-0.1.dist-info/top_level.txt
