Metadata-Version: 2.0
Name: puppy-pubsub
Version: 0.1
Summary: Pub/Sub that makes your project simpler, not more complicated
Home-page: http://github.com/crgirard/puppy
Author: Corey Girard
Author-email: corey.r.girard@gmail.com
License: MIT
Platform: UNKNOWN
Classifier: License :: OSI Approved :: MIT License
Classifier: Intended Audience :: Developers
Classifier: Development Status :: 3 - Alpha
